pythoncolourlibraryV1/__init__.py
pythoncolourlibraryV1-1.0.0.dist-info/METADATA
pythoncolourlibraryV1-1.0.0.dist-info/WHEEL
pythoncolourlibraryV1-1.0.0.dist-info/top_level.txt
pythoncolourlibraryV1-1.0.0.dist-info/RECORD
