Metadata-Version: 2.1
Name: pythoncolourlibraryV1
Version: 1.0.0
Summary: Modern Python Package To Handle Colors in Python
Home-page: UNKNOWN
Author: knwnLegend
Author-email: nick.faltermeier@gmx.de
License: UNKNOWN
Keywords: python
Platform: UNKNOWN
Classifier: Operating System :: Microsoft :: Windows
